lumericpy/__init__.py
lumericpy/getModeData.py
lumericpy/layoutMethods.py
lumericpy/magneto_optics.py
lumericpy/plotting.py
lumericpy-1.0.0.dist-info/METADATA
lumericpy-1.0.0.dist-info/WHEEL
lumericpy-1.0.0.dist-info/top_level.txt
lumericpy-1.0.0.dist-info/RECORD
