Metadata-Version: 2.4
Name: lumericpy
Version: 1.0.0
Summary: LumericPy: A Python package for Lumerical FDTD and MODE Solutions
Author: Ameya Velankar
Author-email: <velankar@uw.edu>
Keywords: python,lumerical,importlib,sys,lumapi
Requires-Dist: numpy
Requires-Dist: matplotlib
Dynamic: author
Dynamic: author-email
Dynamic: description
Dynamic: keywords
Dynamic: requires-dist
Dynamic: summary
